ratchets/__init__.py
ratchets/__main__.py
ratchets/abstracted_tests.py
ratchets/caching.py
ratchets/results.py
ratchets/run_tests.py
ratchets/validate.py
ratchets-0.2.11.dist-info/licenses/LICENSE
ratchets-0.2.11.dist-info/METADATA
ratchets-0.2.11.dist-info/WHEEL
ratchets-0.2.11.dist-info/top_level.txt
ratchets-0.2.11.dist-info/RECORD
