Metadata-Version: 2.4
Name: ratchets
Version: 0.2.11
Summary: Ratcheted testing in Python.
Author-email: Andrew Laack <andrew@laack.co>
License: GPL-3.0-only
Project-URL: Homepage, https://github.com/andrewlaack/ratchets
Project-URL: Repository, https://github.com/andrewlaack/ratchets
Requires-Python: >=3.7
License-File: LICENSE
Requires-Dist: pathspec~=0.12.1
Requires-Dist: toml~=0.10.2
Provides-Extra: test
Requires-Dist: pytest>=7.0; extra == "test"
Dynamic: license-file
